LICENSE.txt
MANIFEST.in
README.md
setup.py
socket_api2/__init__.py
socket_api2/client.py
socket_api2/server.py
socket_api2/utils.py
socket_api2.egg-info/PKG-INFO
socket_api2.egg-info/SOURCES.txt
socket_api2.egg-info/dependency_links.txt
socket_api2.egg-info/requires.txt
socket_api2.egg-info/top_level.txt