Metadata-Version: 2.1
Name: socket-api2
Version: 0.2.0
Summary: Socket Api 2 creates the best connection between a server and client/clients, and its compatible with ngrok (pyngrok)
Home-page: UNKNOWN
Author: Da4ndo
Author-email: da4ndo0@gmail.com
License: UNKNOWN
Keywords: socket_api2,socket,socket_api,socket api,socket api 2
Platform: UNKNOWN
Classifier: Development Status :: 5 - Production/Stable
Classifier: Intended Audience :: Education
Classifier: Operating System :: Microsoft :: Windows :: Windows 10
Classifier: License :: OSI Approved :: MIT License
Classifier: Programming Language :: Python :: 3
License-File: LICENSE.txt
